csvcdc.py
tests/__init__.py
tests/conftest.py
tests/test_csvcdc.py
tests/test_data/test1_base.csv
tests/test_data/test1_delta.csv
csv_cdc-0.1.3.dist-info/LICENSE
csv_cdc-0.1.3.dist-info/METADATA
csv_cdc-0.1.3.dist-info/WHEEL
csv_cdc-0.1.3.dist-info/entry_points.txt
csv_cdc-0.1.3.dist-info/top_level.txt
csv_cdc-0.1.3.dist-info/RECORD
