Metadata-Version: 2.1
Name: csv-cdc
Version: 0.1.3
Summary: A high-performance CSV Change Data Capture tool
Home-page: https://github.com/maurohkcba/csv-cdc
Author: Mauro Bartolomeu dos Reis
Author-email: Mauro Bartolomeu dos Reis <maurohktga@gmail.com>
License: MIT
Project-URL: Homepage, https://github.com/maurohkcba/csv-cdc
Project-URL: Bug Reports, https://github.com/maurohkcba/csv-cdc/issues
Project-URL: Source, https://github.com/maurohkcba/csv-cdc
Project-URL: Documentation, https://github.com/maurohkcba/csv-cdc/wiki
Keywords: csv,diff,cdc,change-data-capture,data-comparison
Classifier: Development Status :: 5 - Production/Stable
Classifier: Intended Audience :: Developers
Classifier: License :: OSI Approved :: MIT License
Classifier: Operating System :: OS Independent
Classifier: Programming Language :: Python :: 3
Classifier: Programming Language :: Python :: 3.7
Classifier: Programming Language :: Python :: 3.8
Classifier: Programming Language :: Python :: 3.9
Classifier: Programming Language :: Python :: 3.10
Classifier: Programming Language :: Python :: 3.11
Classifier: Topic :: Software Development :: Libraries :: Python Modules
Classifier: Topic :: Utilities
Classifier: Topic :: Text Processing
Requires-Python: >=3.7
License-File: LICENSE
Requires-Dist: pandas >=1.3.0
Requires-Dist: numpy >=1.21.0
Requires-Dist: polars >=0.15.0
Requires-Dist: xxhash >=3.0.0
Requires-Dist: colorama >=0.4.4
Requires-Dist: tqdm >=4.62.0
Provides-Extra: dev
Requires-Dist: pytest >=6.0 ; extra == 'dev'
Requires-Dist: pytest-cov >=2.0 ; extra == 'dev'
Requires-Dist: black >=22.0 ; extra == 'dev'
Requires-Dist: isort >=5.0 ; extra == 'dev'
Requires-Dist: flake8 >=4.0 ; extra == 'dev'
Requires-Dist: mypy >=0.950 ; extra == 'dev'
Requires-Dist: pre-commit >=2.0 ; extra == 'dev'
Provides-Extra: test
Requires-Dist: pytest >=6.0 ; extra == 'test'
Requires-Dist: pytest-cov >=2.0 ; extra == 'test'
